mtgdata/__init__.py
mtgdata/__main__.py
mtgdata/scryfall.py
mtgdata/scryfall_convert.py
mtgdata/util/__init__.py
mtgdata/util/hdf5.py
mtgdata-0.3.0.dist-info/METADATA
mtgdata-0.3.0.dist-info/WHEEL
mtgdata-0.3.0.dist-info/top_level.txt
mtgdata-0.3.0.dist-info/RECORD
