Metadata-Version: 2.4
Name: mtgdata
Version: 0.3.0
Summary: MTG image dataset with automatic image scraping and conversion.
Author-email: Nathan Juraj Michlo <NathanJMichlo@gmail.com>
Project-URL: Homepage, https://github.com/nmichlo/mtg-dataset
Classifier: License :: OSI Approved :: MIT License
Classifier: Operating System :: OS Independent
Classifier: Programming Language :: Python :: 3.9
Classifier: Programming Language :: Python :: 3.10
Classifier: Programming Language :: Python :: 3.11
Classifier: Programming Language :: Python :: 3.12
Classifier: Programming Language :: Python :: 3.13
Classifier: Intended Audience :: Science/Research
Requires-Python: >=3.9
Requires-Dist: duckdb
Requires-Dist: pytz
Requires-Dist: requests
Requires-Dist: doorway[extras]~=0.6.0
Requires-Dist: pillow
Provides-Extra: convert
Requires-Dist: h5py; extra == "convert"
Requires-Dist: numpy; extra == "convert"
Requires-Dist: pillow; extra == "convert"
Requires-Dist: tqdm; extra == "convert"
Requires-Dist: torch; extra == "convert"
